PyQt6/Qt6/qsci/api/python/PyQt6-NetworkAuth.api
PyQt6/QtNetworkAuth.abi3.so
PyQt6/QtNetworkAuth.pyi
PyQt6/bindings/QtNetworkAuth/QtNetworkAuth.toml
PyQt6/bindings/QtNetworkAuth/QtNetworkAuthmod.sip
PyQt6/bindings/QtNetworkAuth/qabstractoauth.sip
PyQt6/bindings/QtNetworkAuth/qabstractoauth2.sip
PyQt6/bindings/QtNetworkAuth/qabstractoauthreplyhandler.sip
PyQt6/bindings/QtNetworkAuth/qoauth1.sip
PyQt6/bindings/QtNetworkAuth/qoauth1signature.sip
PyQt6/bindings/QtNetworkAuth/qoauth2authorizationcodeflow.sip
PyQt6/bindings/QtNetworkAuth/qoauth2deviceauthorizationflow.sip
PyQt6/bindings/QtNetworkAuth/qoauthhttpserverreplyhandler.sip
PyQt6/bindings/QtNetworkAuth/qoauthoobreplyhandler.sip
PyQt6/bindings/QtNetworkAuth/qoauthurischemereplyhandler.sip
pyqt6_networkauth-6.10.0.dist-info/licenses/LICENSE
pyqt6_networkauth-6.10.0.dist-info/WHEEL
pyqt6_networkauth-6.10.0.dist-info/METADATA
pyqt6_networkauth-6.10.0.dist-info/RECORD
